scm203lab367101691/__init__.py
scm203lab367101691/lab3mod16101691.py
scm203lab367101691-0.1.0.dist-info/METADATA
scm203lab367101691-0.1.0.dist-info/WHEEL
scm203lab367101691-0.1.0.dist-info/top_level.txt
scm203lab367101691-0.1.0.dist-info/RECORD
