Metadata-Version: 2.4
Name: scm203lab367101691
Version: 0.1.0
Summary: Find the greatest common divisor and find integers x,y such that ax + by = gcd(a,b).
Home-page: https://github.com/yourusername/scm203lab367101691
Author: Khing
Author-email: anchitha2005@gmail.com
Requires-Python: >=3.7
Dynamic: author
Dynamic: author-email
Dynamic: description
Dynamic: description-content-type
Dynamic: home-page
Dynamic: requires-python
Dynamic: summary
